viawidgets/__init__.py
viawidgets/base.py
viawidgets/models.py
viawidgets/themes.py
viawidgets/widgets.py
viawidgets/CSS/GroupingConstraintsWidget.css
viawidgets/JS/GroupingConstraintsWidget.js
viawidgets/JS/HistogramRangeFilter.js
viawidgets/JS/LinePatternSearcher.js
viawidgets/JS/ScatterplotCategorizer.js
viawidgets/JS/ScatterplotSelector.js
viawidgets-0.1.2.dist-info/METADATA
viawidgets-0.1.2.dist-info/WHEEL
viawidgets-0.1.2.dist-info/RECORD
