Metadata-Version: 2.4
Name: viawidgets
Version: 0.1.2
Summary: A collection of simple custom widgets built with AnyWidget.
Author-email: Madhav Poddar <madhav.poddar19@gmail.com>
License: MIT
Requires-Python: >=3.8
Requires-Dist: anywidget>=0.9.0
Requires-Dist: dtaidistance>=2.0.0
Requires-Dist: numpy>=1.21.0
Requires-Dist: pandas>=1.0.0
Requires-Dist: pyarrow>=6.0.0
Requires-Dist: traitlets>=5.0.0
Provides-Extra: dev
Requires-Dist: anywidget[dev]; extra == 'dev'
Requires-Dist: drawdata; extra == 'dev'
Requires-Dist: marimo; extra == 'dev'
Requires-Dist: scikit-learn; extra == 'dev'
